custom_cache_page/__init__.py
custom_cache_page/conf.py
custom_cache_page/decorators.py
custom_cache_page/indexes.py
custom_cache_page/keys.py
custom_cache_page/surrogates.py
custom_cache_page/backends/__init__.py
custom_cache_page/backends/base.py
custom_cache_page/backends/composite.py
custom_cache_page/backends/django.py
django_custom_cache_page-1.0.0.dist-info/licenses/LICENSE
tests/__init__.py
tests/test_backends.py
tests/test_conf.py
tests/test_decorators.py
tests/test_indexes.py
tests/test_indexes_integration.py
tests/test_keys.py
tests/test_surrogates.py
django_custom_cache_page-1.0.0.dist-info/METADATA
django_custom_cache_page-1.0.0.dist-info/WHEEL
django_custom_cache_page-1.0.0.dist-info/top_level.txt
django_custom_cache_page-1.0.0.dist-info/RECORD
